gmas/__init__.py
gmas/version.py
gmas-0.1.0.dist-info/WHEEL
gmas-0.1.0.dist-info/METADATA
gmas-0.1.0.dist-info/RECORD
