Metadata-Version: 2.1
Name: gmas
Version: 0.1.0
Summary: Give me a server.
License: GNU
Author: laixintao
Author-email: laixintaoo@gmail.com
Requires-Python: >=3.9,<4.0
Classifier: License :: Other/Proprietary License
Classifier: Programming Language :: Python :: 3
Classifier: Programming Language :: Python :: 3.9
